setup.py
support_th/__init__.py
support_th/support_th.py
support_th.egg-info/PKG-INFO
support_th.egg-info/SOURCES.txt
support_th.egg-info/dependency_links.txt
support_th.egg-info/not-zip-safe
support_th.egg-info/top_level.txt