Metadata-Version: 1.0
Name: support-th
Version: 0.1
Summary: clinical trial information retriver
Home-page: http://github.com/tongling/clinicaltrial
Author: fxl
Author-email: 1372734585@qq.com
License: MIT
Platform: UNKNOWN
